{"product_url": "https://www.clydepaperandprint.com/products/ppc-lasercopier-a4-white-copy-paper/1205/", "product_name": "PPC Lasercopier A4 White Copy Paper", "description": "PPC Lasercopier Paper is a multipurpose white copier paper for everyday use. Great quality, reliable, budget option.", "price": "4.29", "currency": "£", "product_rating": null, "Color": ["White"], "availability": true, "shipping": true, "delivery_date": null, "delivery_cost": null, "warranty": false, "warranty_policy": null, "condition": "new", "image": "/userfiles/products/n_1205-1.jpg?v=1676551370", "latest_reviews": []}